Yudi/_init_.py
yudi-0.0.1.dist-info/METADATA
yudi-0.0.1.dist-info/WHEEL
yudi-0.0.1.dist-info/top_level.txt
yudi-0.0.1.dist-info/RECORD
