Metadata-Version: 2.4
Name: yudi
Version: 0.0.1
Summary: A simple voice assistant created speech recognition and text to speech
Author: Yuvraj Dixit
Author-email: yuvrajdixit017@gmail.com
Dynamic: author
Dynamic: author-email
Dynamic: summary
